AUTHORS
ChangeLog
Jenkinsfile
README.md
debug-install.sh
jenkins.sh
make.sh
requirements.txt
rsync-code.sh
setup.cfg
setup.py
test-requirements.txt
tox.ini
.github/workflows/publish-to-test-pypi.yml
chaoshen_toolbox/__init__.py
chaoshen_toolbox.egg-info/PKG-INFO
chaoshen_toolbox.egg-info/SOURCES.txt
chaoshen_toolbox.egg-info/dependency_links.txt
chaoshen_toolbox.egg-info/entry_points.txt
chaoshen_toolbox.egg-info/not-zip-safe
chaoshen_toolbox.egg-info/pbr.json
chaoshen_toolbox.egg-info/requires.txt
chaoshen_toolbox.egg-info/top_level.txt
chaoshen_toolbox/config/base.py
chaoshen_toolbox/config/support.py
chaoshen_toolbox/model/network.py
chaoshen_toolbox/scripts/__init__.py
chaoshen_toolbox/scripts/config.py
chaoshen_toolbox/scripts/docker/add_sudo_command_to_sudoers.py
chaoshen_toolbox/scripts/docker/run_rm.py
chaoshen_toolbox/scripts/network/config_static_ip.py
chaoshen_toolbox/scripts/openstack/log_delete_req.py
chaoshen_toolbox/scripts/windows/find_crlf_files.py
chaoshen_toolbox/utils/__init__.py
chaoshen_toolbox/utils/common.py
chaoshen_toolbox/utils/file.py
chaoshen_toolbox/utils/linux.py
chaoshen_toolbox/utils/my_decorator.py
chaoshen_toolbox/utils/windows.py
python-demo/device/zn600.py
python-demo/system/eventlet_/wait-event/readme.md
python-demo/system/eventlet_/wait-event/wait-demo.py
python-demo/system/eventlet_/wait-event/cinder/db_base.py
python-demo/system/eventlet_/wait-event/cinder/message_api.py
python-demo/system/eventlet_/wait-event/cinder/message_field.py
python-demo/system/eventlet_/wait-event/cinder/send-event.py
python-demo/system/eventlet_/wait-event/nova/objects.py
python-demo/system/eventlet_/wait-event/nova/wait-event-2.py
python-demo/system/eventlet_/wait-event/nova/wait-event-3.py
tools/cs-docker-tailf-container-log.sh
tools/cs-filter-comment.sh
tools/cs-git-push-use-token.sh
tools/cs-hello.sh
tools/cs-permit-root-ssh.sh
tools/cs-task-watcher.sh
tools/windows/Get-NetIpConfigration.ps1
user_config/network.yaml